LICENSE
README.md
setup.py
clashlite/__init__.py
clashlite/clash.py
clashlite.egg-info/PKG-INFO
clashlite.egg-info/SOURCES.txt
clashlite.egg-info/dependency_links.txt
clashlite.egg-info/requires.txt
clashlite.egg-info/top_level.txt