Metadata-Version: 2.2
Name: clashlite
Version: 0.1.0
Summary: Managing Clash proxy core elegantly with python.
Home-page: https://github.com/LanYangYang321/clash-for-python
Author: LanYangYang321
Author-email: lanyyontop@gmail.com
License: MIT
Keywords: clash,clashlite,pyclash,ClashForPython,liteclash,clashpy
Platform: Windows
Requires-Python: >=3.7
License-File: LICENSE
Requires-Dist: requests
Requires-Dist: pyyaml
Dynamic: author
Dynamic: author-email
Dynamic: description
Dynamic: description-content-type
Dynamic: home-page
Dynamic: keywords
Dynamic: license
Dynamic: platform
Dynamic: requires-dist
Dynamic: requires-python
Dynamic: summary
